NanopolishComp/Eventalign_collapse.py
NanopolishComp/Freq_meth_calculate.py
NanopolishComp/__init__.py
NanopolishComp/__main__.py
NanopolishComp/common.py
NanopolishComp-0.6.2.dist-info/METADATA
NanopolishComp-0.6.2.dist-info/RECORD
NanopolishComp-0.6.2.dist-info/WHEEL
NanopolishComp-0.6.2.dist-info/entry_points.txt
NanopolishComp-0.6.2.dist-info/top_level.txt
