Metadata-Version: 2.1
Name: NanopolishComp
Version: 0.6.2
Summary: NanopolishComp is a Python3 package for downstream analyses of Nanopolish output files
Home-page: https://github.com/a-slide/NanopolishComp
Author: Adrien Leger
Author-email: aleg@ebi.ac.uk
License: MIT
Platform: UNKNOWN
Classifier: Development Status :: 3 - Alpha
Classifier: Intended Audience :: Science/Research
Classifier: Topic :: Scientific/Engineering :: Bio-Informatics
Classifier: License :: OSI Approved :: MIT License
Classifier: Programming Language :: Python :: 3
Requires-Python: >=3.3
Requires-Dist: numpy (>=1.14.0)
Requires-Dist: tqdm (>=4.23.4)
